wavefront_cli/__init__.py
wavefront_cli/cli.py
wavefront_cli/commands/__init__.py
wavefront_cli/commands/base.py
wavefront_cli/commands/configure.py
wavefront_cli/commands/hello.py
wavefront_cli/commands/install.py
wavefront_cli/commands/integration.py
wavefront_cli/integrations/__init__.py
wavefront_cli/integrations/base.py
wavefront_cli/integrations/example.py
wavefront_cli/integrations/statsd.py
wavefront_cli/integrations/wavefront.py
wavefront_cli/lib/__init__.py
wavefront_cli/lib/agent.py
wavefront_cli/lib/api.py
wavefront_cli/lib/auth.py
wavefront_cli/lib/aws.py
wavefront_cli/lib/message.py
wavefront_cli/lib/proxy.py
wavefront_cli/lib/system.py
wavefront_cli/lib/util.py
wavefront_cli-0.1.2.dist-info/LICENSE
wavefront_cli-0.1.2.dist-info/METADATA
wavefront_cli-0.1.2.dist-info/WHEEL
wavefront_cli-0.1.2.dist-info/entry_points.txt
wavefront_cli-0.1.2.dist-info/top_level.txt
wavefront_cli-0.1.2.dist-info/RECORD
